Metadata-Version: 2.4
Name: mv-pypowerstore
Version: 3.4.1.3
Summary: Python Library for Dell PowerStore Modified by Moviri for use with Dynatrace extensions.
Home-page: https://github.com/dell/python-powerstore
Author: Moviri
Author-email: dynatrace_extensions@moviri.com
Classifier: License :: OSI Approved :: Apache Software License
License-File: LICENSE
Requires-Dist: urllib3>=1.26.7
Requires-Dist: requests>=2.23.0
Dynamic: author
Dynamic: author-email
Dynamic: classifier
Dynamic: home-page
Dynamic: license-file
Dynamic: requires-dist
Dynamic: summary
